README.rst
setup.py
abathur/__init__.py
abathur/abathur.py
abathur/alias.py
abathur/builder.py
abathur/constant.py
abathur/entrypoint.py
abathur.egg-info/PKG-INFO
abathur.egg-info/SOURCES.txt
abathur.egg-info/dependency_links.txt
abathur.egg-info/entry_points.txt
abathur.egg-info/requires.txt
abathur.egg-info/top_level.txt
abathur/commands/__init__.py
abathur/commands/add_command.py
abathur/commands/base_command.py
abathur/commands/build_command.py
abathur/commands/list_command.py
abathur/commands/remove_command.py