Metadata-Version: 1.1
Name: abathur
Version: 1.0.1
Summary: Template manager
Home-page: https://github.com/yeyuexia/abathur
Author: yeyuexia
Author-email: yyxworld@gmail.com
License: MIT
Keywords: manage project templates and build project with template
Platform: UNKNOWN
Classifier: Development Status :: 3 - Alpha
Classifier: Intended Audience :: Developers
Classifier: Topic :: Software Development :: Build Tools
Classifier: License :: OSI Approved :: MIT License
Classifier: Programming Language :: Python :: 3.6
